cli/__init__.py
cli/main.py
hypha_artifact/__init__.py
hypha_artifact/artifact_file.py
hypha_artifact/async_artifact_file.py
hypha_artifact/async_hypha_artifact_compat.py
hypha_artifact/classes.py
hypha_artifact/hypha_artifact.py
hypha_artifact/py.typed
hypha_artifact/sync_utils.py
hypha_artifact/transfer_progress.py
hypha_artifact/utils.py
hypha_artifact/async_hypha_artifact/__init__.py
hypha_artifact/async_hypha_artifact/_fs.py
hypha_artifact/async_hypha_artifact/_io.py
hypha_artifact/async_hypha_artifact/_multipart.py
hypha_artifact/async_hypha_artifact/_remote_methods.py
hypha_artifact/async_hypha_artifact/_state.py
hypha_artifact/async_hypha_artifact/_utils.py
hypha_artifact/async_hypha_artifact/types.py
hypha_artifact-0.2.5.dist-info/licenses/LICENSE
hypha_artifact-0.2.5.dist-info/METADATA
hypha_artifact-0.2.5.dist-info/WHEEL
hypha_artifact-0.2.5.dist-info/entry_points.txt
hypha_artifact-0.2.5.dist-info/top_level.txt
hypha_artifact-0.2.5.dist-info/RECORD
