Metadata-Version: 2.4
Name: hypha-artifact
Version: 0.2.5
Summary: Hypha Artifact package, used with Hypha.
Author-email: Hugo Dettner Källander <hugokallander@gmail.com>
License-Expression: MIT
Requires-Python: >=3.11
License-File: LICENSE
Requires-Dist: httpx>=0.24.0
Requires-Dist: python-dotenv>=0.21.0
Requires-Dist: hypha_rpc>=0.20.54
Requires-Dist: pyyaml>=6.0.1
Requires-Dist: tqdm>=4.67.1
Requires-Dist: anyio==4.11.0
Provides-Extra: cli
Requires-Dist: fire>=0.6.0; extra == "cli"
Dynamic: license-file
